amorce/__init__.py
amorce/client.py
amorce/crypto.py
amorce/envelope.py
amorce/exceptions.py
amorce/mcp_helpers.py
amorce/models.py
amorce/verification.py
amorce/well_known.py
amorce/core/__init__.py
amorce/core/async_client.py
amorce_sdk-0.2.2.dist-info/METADATA
amorce_sdk-0.2.2.dist-info/WHEEL
amorce_sdk-0.2.2.dist-info/top_level.txt
amorce_sdk-0.2.2.dist-info/RECORD
