Metadata-Version: 2.4
Name: amorce-sdk
Version: 0.2.2
Summary: Official Python SDK for the Amorce Agent Transaction Protocol (AATP)
Home-page: https://github.com/trebortGolin/amorce_py_sdk
Author: Athena Architecture
Author-email: dev@amorce.io
Classifier: Programming Language :: Python :: 3
Classifier: Programming Language :: Python :: 3.9
Classifier: Programming Language :: Python :: 3.10
Classifier: Programming Language :: Python :: 3.11
Classifier: Programming Language :: Python :: 3.12
Classifier: Programming Language :: Python :: 3.13
Classifier: License :: OSI Approved :: MIT License
Classifier: Operating System :: OS Independent
Classifier: Intended Audience :: Developers
Classifier: Topic :: Software Development :: Libraries :: Python Modules
Classifier: Development Status :: 4 - Beta
Requires-Python: >=3.9
Requires-Dist: requests>=2.31.0
Requires-Dist: httpx>=0.25.0
Requires-Dist: tenacity>=8.0.0
Requires-Dist: cryptography>=41.0.0
Requires-Dist: pydantic>=2.0.0
Provides-Extra: dev
Requires-Dist: pytest>=7.4.0; extra == "dev"
Requires-Dist: pytest-asyncio>=0.21.0; extra == "dev"
Requires-Dist: pytest-cov>=4.1.0; extra == "dev"
Requires-Dist: respx>=0.20.0; extra == "dev"
Requires-Dist: mypy>=1.5.0; extra == "dev"
Provides-Extra: gcp
Requires-Dist: google-cloud-secret-manager>=2.16.0; extra == "gcp"
Requires-Dist: firebase-admin>=6.2.0; extra == "gcp"
Dynamic: author
Dynamic: author-email
Dynamic: classifier
Dynamic: description
Dynamic: description-content-type
Dynamic: home-page
Dynamic: provides-extra
Dynamic: requires-dist
Dynamic: requires-python
Dynamic: summary
